gutta/VERSION
gutta/__init__.py
gutta/cli.py
gutta/webserver.py
gutta/builder/__init__.py
gutta/builder/addresses.py
gutta/builder/assets.py
gutta/builder/blobs.py
gutta/builder/dates.py
gutta/builder/exceptions.py
gutta/builder/extras.py
gutta/builder/feeds.py
gutta/builder/gutta_info.py
gutta/builder/localpaths.py
gutta/builder/mountpoints.py
gutta/builder/pages.py
gutta/builder/resources.py
gutta/builder/specs.py
gutta/builder/style.py
gutta/builder/wcnode.py
gutta/builder/wctree.py
gutta/builder/resources/Thumbs.db
gutta/builder/resources/gutta.scss
gutta/builder/resources/gutta_logo.png
gutta/builder/resources/gutta_logo.svg
gutta/builder/resources/gutta_logo128.png
gutta/builder/resources/gutta_logo24.png
gutta/builder/resources/gutta_logo32.png
gutta/builder/resources/gutta_logo64.png
gutta/builder/resources/gutta_logo_icon.svg
gutta/builder/templates/autogenerated_warning.jinja
gutta/builder/templates/base.jinja
gutta/builder/templates/core.jinja
gutta/builder/templates/extra.jinja
gutta/builder/templates/gallery.jinja
gutta/builder/templates/gallery_inner.jinja
gutta/builder/templates/opengraph.jinja
gutta/builder/templates/redirect.jinja
gutta/builder/templates/scroll.jinja
gutta/builder/templates/scroll_inner.jinja
gutta/builder/templates/section.jinja
gutta/builder/templates/toc_inner.jinja
gutta/builder/templates/trickle_inner.jinja
gutta/sample_comic/_assets/gutta_tutorial/gutta_logo.png
gutta/sample_comic/_assets/gutta_tutorial/gutta_logo128.png
gutta/sample_comic/_assets/gutta_tutorial/gutta_logo_icon.svg
gutta/sample_comic/_assets/gutta_tutorial/gutta_tutorial00.webp
gutta/sample_comic/_assets/gutta_tutorial/gutta_tutorial01.webp
gutta/sample_comic/_assets/gutta_tutorial/gutta_tutorial02.webp
gutta/sample_comic/_assets/gutta_tutorial/gutta_tutorial03.webp
gutta/sample_comic/_source/about.md
gutta/sample_comic/_source/style.scss
gutta/sample_comic/_source/vars.scss
gutta/sample_comic/_source/webcomic.yaml
gutta-0.1.10.dist-info/LICENSE.txt
gutta-0.1.10.dist-info/METADATA
gutta-0.1.10.dist-info/WHEEL
gutta-0.1.10.dist-info/entry_points.txt
gutta-0.1.10.dist-info/top_level.txt
gutta-0.1.10.dist-info/RECORD
