Metadata-Version: 2.1
Name: gutta
Version: 0.1.10
Summary: A simple, modular static site builder for webcomics.
Author-email: cancrizans <cancrizans.canon@gmail.com>
Project-URL: Homepage, https://github.com/cancrizans/gutta
Project-URL: Bug Tracker, https://github.com/cancrizans/gutta/issues
Classifier: Programming Language :: Python :: 3
Classifier: License :: OSI Approved :: MIT License
Classifier: Operating System :: OS Independent
Requires-Python: >=3.10
License-File: LICENSE.txt
Requires-Dist: click
Requires-Dist: jinja2
Requires-Dist: pyyaml
Requires-Dist: oyaml
Requires-Dist: markdown
Requires-Dist: libsass
Requires-Dist: imagesize
Requires-Dist: numpy
Requires-Dist: python-dateutil
Requires-Dist: feedgen
Requires-Dist: pytz
Requires-Dist: watchfiles
